{
    "id": 1018934501,
    "href": "https://nvdbapiles-v3.atlas.vegvesen.no/vegobjekter/540/1018934501/1",
    "metadata": {
        "type": {
            "id": 540,
            "navn": "Trafikkmengde"
        },
        "versjon": 1,
        "startdato": "2024-01-10",
        "sist_modifisert": "2024-02-27T10:18:42"
    },
    "egenskaper": [
        {
            "id": 120540,
            "navn": "Liste av lokasjonsattributt",
            "egenskapstype": "Liste",
            "datatype": "Liste",
            "innhold": [
                {
                    "id": 100540,
                    "navn": "StrekningTilknytning",
                    "egenskapstype": "Stedfesting",
                    "datatype": "GeomLinje eller Kurve",
                    "stedfestingstype": "Linje",
                    "veglenkesekvensid": 2394247,
                    "startposisjon": 0.0,
                    "sluttposisjon": 1.0,
                    "kjørefelt": []
                }
            ]
        },
        {
            "id": 4621,
            "navn": "År, gjelder for",
            "egenskapstype": "Heltall",
            "datatype": "Tall",
            "verdi": 2023
        },
        {
            "id": 4623,
            "navn": "ÅDT, total",
            "egenskapstype": "Heltall",
            "datatype": "Tall",
            "verdi": 7000
        },
        {
            "id": 4624,
            "navn": "ÅDT, andel lange kjøretøy",
            "egenskapstype": "Heltall",
            "datatype": "Tall",
            "verdi": 7,
            "enhet": {
                "id": 22,
                "navn": "Prosent",
                "kortnavn": "%"
            }
        },
        {
            "id": 4625,
            "navn": "Grunnlag for ÅDT",
            "egenskapstype": "Tekstenum",
            "datatype": "FlerverdiAttributt, Tekst",
            "verdi": "Skjønn",
            "enum_id": 5580
        }
    ],
    "geometri": {
        "wkt": "LINESTRING Z(273619.781 7042013.359 33.089, 273610.881 7042025.355 32.957, 273587.477 7042041.025 31.583, 273576.686 7042048.361 30.931, 273566.57 7042055.231 30.32, 273556.432 7042062.07 29.709, 273546.251 7042068.847 29.098, 273536.009 7042075.528 28.486, 273525.685 7042082.083 27.875, 273515.262 7042088.478 27.264, 273501.866 7042096.323 26.488, 273488.29 7042103.85 25.713, 273474.54 7042111.057 24.937, 273460.625 7042117.938 24.161, 273446.552 7042124.489 23.385, 273432.329 7042130.709 22.61, 273424.335 7042134.032 22.177, 273417.963 7042136.592 21.84, 273403.464 7042142.137 21.121, 273402.961 7042142.323 21.097, 273388.838 7042147.339 20.462, 273381.306 7042149.868 20.149, 273374.093 7042152.196 19.864, 273359.398 7042156.658 19.332, 273344.282 7042160.862 18.849, 273337.263 7042162.684 18.646, 273329.232 7042164.668 18.432, 273314.927 7042167.939 18.092, 273314.097 7042168.118 18.074, 273298.885 7042171.213 17.778, 273292.421 7042172.416 17.67, 273283.604 7042173.949 17.541, 273268.264 7042176.324 17.364, 273252.872 7042178.339 17.248, 273247.004 7042179.01 17.22, 273237.436 7042179.99 17.181, 273221.966 7042181.279 17.117, 273206.47 7042182.204 17.054, 273190.956 7042182.764 16.991, 273175.434 7042182.96 16.927, 273159.911 7042182.79 16.864, 273144.397 7042182.256 16.801, 273128.9 7042181.358 16.738, 273113.427 7042180.094 16.674, 273097.989 7042178.469 16.611, 273082.593 7042176.48 16.548, 273067.249 7042174.13 16.484, 273051.963 7042171.42 16.421, 273036.746 7042168.351 16.358, 273024.908 7042165.71 16.308, 273013.113 7042162.879 16.259, 273005.356 7042160.921 16.225, 273001.358 7042159.885 16.208, 272989.639 7042156.757 16.15, 272977.949 7042153.521 16.083, 272966.281 7042150.204 16.005, 272954.629 7042146.834 15.918, 272942.984 7042143.437 15.821, 272937.444 7042141.819 15.772, 272869.725 7042122.038 14.988, 272802.012 7042102.258 13.872, 272743.132 7042085.058 12.612)",
        "srid": 5973,
        "egengeometri": false
    },
    "lokasjon": {
        "kommuner": [
            5001
        ],
        "fylker": [
            50
        ],
        "kontraktsområder": [
            {
                "id": 1004758086,
                "nummer": 9401,
                "navn": "9401 Trondheim 2020-2025 (f.o.m. 01.09.2023)"
            },
            {
                "id": 1007479425,
                "nummer": 9451,
                "navn": "9451 Elektrokontrakt Trøndelag 2022-2026"
            },
            {
                "id": 1009144004,
                "nummer": 9437,
                "navn": "9437 Tunnelrenhold midt 2020-2025"
            },
            {
                "id": 1019226085,
                "nummer": 9405,
                "navn": "DK 9405 Trøndelag sør"
            },
            {
                "id": 1019330755,
                "nummer": 9481,
                "navn": "9481 Rekkverk Trøndelag og Møre og Romsdal 2023-2024"
            }
        ],
        "riksvegruter": [
            {
                "id": 1017625546,
                "enumid": 20296,
                "riksvegrute": "Rute 6a: E6 Oslo - Trondheim",
                "nummer": "6a",
                "navn": "RUTE6A"
            }
        ],
        "gater": [],
        "vegsystemreferanser": [
            {
                "vegsystem": {
                    "id": 1002158582,
                    "versjon": 1,
                    "vegkategori": "R",
                    "fase": "V",
                    "nummer": 706
                },
                "strekning": {
                    "id": -1,
                    "versjon": -1,
                    "strekning": 2,
                    "delstrekning": 1,
                    "arm": false,
                    "adskilte_løp": "Mot",
                    "adskilte_løp_nummer": "1-2",
                    "trafikantgruppe": "K",
                    "fra_meter": 2638.423,
                    "til_meter": 3570.423,
                    "retning": "MED"
                },
                "kortform": "RV706 S2D1 m2638-3570"
            }
        ],
        "stedfestinger": [
            {
                "type": "Linje",
                "veglenkesekvensid": 2394247,
                "startposisjon": 0.0,
                "sluttposisjon": 1.0,
                "kortform": "0.0-1.0@2394247",
                "kjørefelt": []
            }
        ],
        "geometri": {
            "wkt": "LINESTRING Z(273619.781 7042013.359 33.089, 273610.881 7042025.355 32.957, 273587.477 7042041.025 31.583, 273576.686 7042048.361 30.931, 273566.57 7042055.231 30.32, 273556.432 7042062.07 29.709, 273546.251 7042068.847 29.098, 273536.009 7042075.528 28.486, 273525.685 7042082.083 27.875, 273515.262 7042088.478 27.264, 273501.866 7042096.323 26.488, 273488.29 7042103.85 25.713, 273474.54 7042111.057 24.937, 273460.625 7042117.938 24.161, 273446.552 7042124.489 23.385, 273432.329 7042130.709 22.61, 273424.335 7042134.032 22.177, 273417.963 7042136.592 21.84, 273403.464 7042142.137 21.121, 273402.961 7042142.323 21.097, 273388.838 7042147.339 20.462, 273381.306 7042149.868 20.149, 273374.093 7042152.196 19.864, 273359.398 7042156.658 19.332, 273344.282 7042160.862 18.849, 273337.263 7042162.684 18.646, 273329.232 7042164.668 18.432, 273314.927 7042167.939 18.092, 273314.097 7042168.118 18.074, 273298.885 7042171.213 17.778, 273292.421 7042172.416 17.67, 273283.604 7042173.949 17.541, 273268.264 7042176.324 17.364, 273252.872 7042178.339 17.248, 273247.004 7042179.01 17.22, 273237.436 7042179.99 17.181, 273221.966 7042181.279 17.117, 273206.47 7042182.204 17.054, 273190.956 7042182.764 16.991, 273175.434 7042182.96 16.927, 273159.911 7042182.79 16.864, 273144.397 7042182.256 16.801, 273128.9 7042181.358 16.738, 273113.427 7042180.094 16.674, 273097.989 7042178.469 16.611, 273082.593 7042176.48 16.548, 273067.249 7042174.13 16.484, 273051.963 7042171.42 16.421, 273036.746 7042168.351 16.358, 273024.908 7042165.71 16.308, 273013.113 7042162.879 16.259, 273005.356 7042160.921 16.225, 273001.358 7042159.885 16.208, 272989.639 7042156.757 16.15, 272977.949 7042153.521 16.083, 272966.281 7042150.204 16.005, 272954.629 7042146.834 15.918, 272942.984 7042143.437 15.821, 272937.444 7042141.819 15.772, 272869.725 7042122.038 14.988, 272802.012 7042102.258 13.872, 272743.132 7042085.058 12.612)",
            "srid": 5973,
            "egengeometri": false
        },
        "lengde": 932.0
    },
    "relasjoner": {}
}