{
    "id": 1018806228,
    "href": "https://nvdbapiles-v3.atlas.vegvesen.no/vegobjekter/540/1018806228/1",
    "metadata": {
        "type": {
            "id": 540,
            "navn": "Trafikkmengde"
        },
        "versjon": 1,
        "startdato": "2024-01-05",
        "sist_modifisert": "2025-01-09T14:45:42"
    },
    "egenskaper": [
        {
            "id": 120540,
            "navn": "Liste av lokasjonsattributt",
            "egenskapstype": "Liste",
            "datatype": "Liste",
            "innhold": [
                {
                    "id": 100540,
                    "navn": "StrekningTilknytning",
                    "egenskapstype": "Stedfesting",
                    "datatype": "GeomLinje eller Kurve",
                    "stedfestingstype": "Linje",
                    "veglenkesekvensid": 42513,
                    "startposisjon": 0.05772283,
                    "sluttposisjon": 0.12646716,
                    "kjørefelt": []
                }
            ]
        },
        {
            "id": 4621,
            "navn": "År, gjelder for",
            "egenskapstype": "Heltall",
            "datatype": "Tall",
            "verdi": 2023
        },
        {
            "id": 4623,
            "navn": "ÅDT, total",
            "egenskapstype": "Heltall",
            "datatype": "Tall",
            "verdi": 5500
        },
        {
            "id": 4624,
            "navn": "ÅDT, andel lange kjøretøy",
            "egenskapstype": "Heltall",
            "datatype": "Tall",
            "verdi": 3,
            "enhet": {
                "id": 22,
                "navn": "Prosent",
                "kortnavn": "%"
            }
        },
        {
            "id": 4625,
            "navn": "Grunnlag for ÅDT",
            "egenskapstype": "Tekstenum",
            "datatype": "FlerverdiAttributt, Tekst",
            "verdi": "Skjønn",
            "enum_id": 5580
        }
    ],
    "geometri": {
        "wkt": "LINESTRING Z(271412 7041624.1 44.834, 271420 7041629.3 44.834, 271428.4 7041635.2 44.934, 271438.5 7041642.5 45.034, 271452.4 7041652.2 45.234, 271462.9 7041659.5 45.234, 271472.2 7041665.9 45.234, 271479.2 7041671 45.334)",
        "srid": 5973,
        "egengeometri": false
    },
    "lokasjon": {
        "kommuner": [
            5001
        ],
        "fylker": [
            50
        ],
        "kontraktsområder": [
            {
                "id": 920262210,
                "nummer": 5006,
                "navn": "5006 Trondheim 2020-2028"
            },
            {
                "id": 1013171445,
                "nummer": 5071,
                "navn": "5071 Skjøtselskontrakt Trondheim"
            },
            {
                "id": 1015016376,
                "nummer": 5051,
                "navn": "E5051 Trøndelag Sør"
            },
            {
                "id": 1016312439,
                "nummer": 5050,
                "navn": "E5050 Signalanlegg Trondheim og Malvik 2022-2024"
            },
            {
                "id": 1016532159,
                "nummer": 9,
                "navn": "Skiltkontrakt Trøndelag FK 2020-2025"
            }
        ],
        "riksvegruter": [],
        "gater": [],
        "vegsystemreferanser": [
            {
                "vegsystem": {
                    "id": 1002159482,
                    "versjon": 1,
                    "vegkategori": "F",
                    "fase": "V",
                    "nummer": 6666
                },
                "strekning": {
                    "id": -1,
                    "versjon": -1,
                    "strekning": 1,
                    "delstrekning": 1,
                    "arm": false,
                    "adskilte_løp": "Nei",
                    "trafikantgruppe": "K",
                    "fra_meter": 2002.625,
                    "til_meter": 2084.625,
                    "retning": "MED"
                },
                "kortform": "FV6666 S1D1 m2003-2085"
            }
        ],
        "stedfestinger": [
            {
                "type": "Linje",
                "veglenkesekvensid": 42513,
                "startposisjon": 0.05772283,
                "sluttposisjon": 0.12646716,
                "kortform": "0.05772283-0.12646716@42513",
                "kjørefelt": []
            }
        ],
        "geometri": {
            "wkt": "LINESTRING Z(271412 7041624.1 44.834, 271420 7041629.3 44.834, 271428.4 7041635.2 44.934, 271438.5 7041642.5 45.034, 271452.4 7041652.2 45.234, 271462.9 7041659.5 45.234, 271472.2 7041665.9 45.234, 271479.2 7041671 45.334)",
            "srid": 5973,
            "egengeometri": false
        },
        "lengde": 82.0
    },
    "relasjoner": {}
}